spark_matcher/__init__.py
spark_matcher/config.py
spark_matcher/table_checkpointer.py
spark_matcher/utils.py
spark_matcher/activelearner/__init__.py
spark_matcher/activelearner/active_learner.py
spark_matcher/blocker/__init__.py
spark_matcher/blocker/block_learner.py
spark_matcher/blocker/blocking_rules.py
spark_matcher/data/__init__.py
spark_matcher/data/acm.csv
spark_matcher/data/datasets.py
spark_matcher/data/dblp.csv
spark_matcher/data/stoxx50.csv
spark_matcher/data/voters_1.csv
spark_matcher/data/voters_2.csv
spark_matcher/deduplicator/__init__.py
spark_matcher/deduplicator/connected_components_calculator.py
spark_matcher/deduplicator/deduplicator.py
spark_matcher/deduplicator/hierarchical_clustering.py
spark_matcher/matcher/__init__.py
spark_matcher/matcher/matcher.py
spark_matcher/matching_base/__init__.py
spark_matcher/matching_base/matching_base.py
spark_matcher/sampler/__init__.py
spark_matcher/sampler/training_sampler.py
spark_matcher/scorer/__init__.py
spark_matcher/scorer/scorer.py
spark_matcher/similarity_metrics/__init__.py
spark_matcher/similarity_metrics/similarity_metrics.py
Spark_Matcher-0.3.2.dist-info/LICENSE
Spark_Matcher-0.3.2.dist-info/METADATA
Spark_Matcher-0.3.2.dist-info/WHEEL
Spark_Matcher-0.3.2.dist-info/top_level.txt
Spark_Matcher-0.3.2.dist-info/RECORD
