Metadata-Version: 2.1
Name: Spark-Matcher
Version: 0.3.2
Summary: Record matching and entity resolution at scale in Spark
Author: Ahmet Bayraktar, Stan Leisink, Frits Hermans
Classifier: Programming Language :: Python :: 3
Classifier: License :: OSI Approved :: MIT License
Classifier: Operating System :: OS Independent
Requires-Python: >=3.7
License-File: LICENSE
Requires-Dist: pandas
Requires-Dist: numpy
Requires-Dist: scikit-learn
Requires-Dist: python-Levenshtein
Requires-Dist: thefuzz
Requires-Dist: modAL-python
Requires-Dist: pytest
Requires-Dist: multipledispatch
Requires-Dist: dill
Requires-Dist: graphframes
Requires-Dist: scipy
Provides-Extra: base
Requires-Dist: pandas; extra == "base"
Requires-Dist: numpy; extra == "base"
Requires-Dist: scikit-learn; extra == "base"
Requires-Dist: python-Levenshtein; extra == "base"
Requires-Dist: thefuzz; extra == "base"
Requires-Dist: modAL-python; extra == "base"
Requires-Dist: pytest; extra == "base"
Requires-Dist: multipledispatch; extra == "base"
Requires-Dist: dill; extra == "base"
Requires-Dist: graphframes; extra == "base"
Requires-Dist: scipy; extra == "base"
Provides-Extra: doc
Requires-Dist: pandas; extra == "doc"
Requires-Dist: numpy; extra == "doc"
Requires-Dist: scikit-learn; extra == "doc"
Requires-Dist: python-Levenshtein; extra == "doc"
Requires-Dist: thefuzz; extra == "doc"
Requires-Dist: modAL-python; extra == "doc"
Requires-Dist: pytest; extra == "doc"
Requires-Dist: multipledispatch; extra == "doc"
Requires-Dist: dill; extra == "doc"
Requires-Dist: graphframes; extra == "doc"
Requires-Dist: scipy; extra == "doc"
Requires-Dist: sphinx; extra == "doc"
Requires-Dist: nbsphinx; extra == "doc"
Requires-Dist: sphinx_rtd_theme; extra == "doc"
Provides-Extra: dev
Requires-Dist: pandas; extra == "dev"
Requires-Dist: numpy; extra == "dev"
Requires-Dist: scikit-learn; extra == "dev"
Requires-Dist: python-Levenshtein; extra == "dev"
Requires-Dist: thefuzz; extra == "dev"
Requires-Dist: modAL-python; extra == "dev"
Requires-Dist: pytest; extra == "dev"
Requires-Dist: multipledispatch; extra == "dev"
Requires-Dist: dill; extra == "dev"
Requires-Dist: graphframes; extra == "dev"
Requires-Dist: scipy; extra == "dev"
Requires-Dist: sphinx; extra == "dev"
Requires-Dist: nbsphinx; extra == "dev"
Requires-Dist: sphinx_rtd_theme; extra == "dev"
Requires-Dist: pyspark; extra == "dev"
Requires-Dist: pyarrow; extra == "dev"
Requires-Dist: jupyterlab; extra == "dev"
